{"trial_id": "0008", "hyperparameters": {"space": [{"class_name": "Int", "config": {"name": "units", "default": null, "conditions": [], "min_value": 16, "max_value": 128, "step": 16, "sampling": "linear"}}, {"class_name": "Float", "config": {"name": "dropout", "default": 0.0, "conditions": [], "min_value": 0.0, "max_value": 0.5, "step": 0.1, "sampling": "linear"}}, {"class_name": "Float", "config": {"name": "learning_rate", "default": 0.0001, "conditions": [], "min_value": 0.0001, "max_value": 0.01, "step": null, "sampling": "log"}}], "values": {"units": 32, "dropout": 0.30000000000000004, "learning_rate": 0.00014791121556251174, "tuner/epochs": 3, "tuner/initial_epoch": 0, "tuner/bracket": 2, "tuner/round": 0}}, "metrics": {"metrics": {"loss": {"direction": "min", "observations": [{"value": [0.004958797246217728], "step": 2}]}, "mae": {"direction": "min", "observations": [{"value": [0.052935827523469925], "step": 2}]}, "val_loss": {"direction": "min", "observations": [{"value": [0.0038191713392734528], "step": 2}]}, "val_mae": {"direction": "min", "observations": [{"value": [0.04831167683005333], "step": 2}]}}}, "score": 0.0038191713392734528, "best_step": 2, "status": "COMPLETED", "message": null}